vripper/__init__.py
vripper/error.py
vripper/download/__init__.py
vripper/download/gdlwrapper.py
vripper/download/imagedownloader.py
vripper/download/postdownloader.py
vripper/download/postprogress.py
vripper/download/threaddownloader.py
vripper/download/threadprogress.py
vripper/enum/__init__.py
vripper/enum/downloadmode.py
vripper/enum/outputformat.py
vripper/enum/processingpriority.py
vripper/forum/__init__.py
vripper/forum/threadfactory.py
vripper/forum/provider/__init__.py
vripper/forum/provider/buondua.py
vripper/forum/provider/dirtyship.py
vripper/forum/provider/nlegs.py
vripper/forum/provider/superbeautygirlx.py
vripper/forum/provider/thaihotmodels.py
vripper/forum/provider/v2ph.py
vripper/forum/provider/vipergirls.py
vripper/model/__init__.py
vripper/model/vimage.py
vripper/model/vparams.py
vripper/model/vpost.py
vripper/model/vthread.py
vripper/parser/__init__.py
vripper/parser/_common.py
vripper/parser/_def.py
vripper/parser/_template.py
vripper/parser/acidimg.py
vripper/parser/damimage.py
vripper/parser/dirtyship.py
vripper/parser/imagebam.py
vripper/parser/imagedecode.py
vripper/parser/imagenimage.py
vripper/parser/imageporter.py
vripper/parser/imagetwist.py
vripper/parser/imagevenue.py
vripper/parser/imagezilla.py
vripper/parser/imgbabes.py
vripper/parser/imgbox.py
vripper/parser/imgclick.py
vripper/parser/imgflare.py
vripper/parser/imghit.py
vripper/parser/imgmoney.py
vripper/parser/imgproof.py
vripper/parser/imgspice.py
vripper/parser/imgtaxi.py
vripper/parser/imgtown.py
vripper/parser/imgzeus.py
vripper/parser/nlegs.py
vripper/parser/photolot.py
vripper/parser/picstate.py
vripper/parser/picszsite.py
vripper/parser/pixhost.py
vripper/parser/pixxxelscc.py
vripper/parser/postimgcc.py
vripper/parser/turboimagehost.py
vripper/parser/uplimg.py
vripper/parser/viprim.py
vripper/postprocess/__init__.py
vripper/postprocess/imgproc.py
vripper-0.5.38.dist-info/METADATA
vripper-0.5.38.dist-info/WHEEL
vripper-0.5.38.dist-info/top_level.txt
vripper-0.5.38.dist-info/RECORD
