Metadata-Version: 2.1
Name: vripper
Version: 0.5.38
Summary: A Python implementation of VRipper
Home-page: UNKNOWN
Author: vka
License: UNKNOWN
Platform: UNKNOWN
Classifier: Programming Language :: Python :: 3
Classifier: Operating System :: OS Independent
Requires-Python: >=3.6
Requires-Dist: requests
Requires-Dist: lxml
Requires-Dist: python-resize-image
Requires-Dist: gallery-dl
Requires-Dist: commmons
